huaweicloudsdkdws/__init__.py
huaweicloudsdkdws/v2/__init__.py
huaweicloudsdkdws/v2/dws_async_client.py
huaweicloudsdkdws/v2/dws_client.py
huaweicloudsdkdws/v2/model/__init__.py
huaweicloudsdkdws/v2/model/action_info.py
huaweicloudsdkdws/v2/model/action_item_vo.py
huaweicloudsdkdws/v2/model/action_sub_item_vo.py
huaweicloudsdkdws/v2/model/add_except_rule_req.py
huaweicloudsdkdws/v2/model/add_queue_user_list_request.py
huaweicloudsdkdws/v2/model/add_queue_user_list_response.py
huaweicloudsdkdws/v2/model/add_workload_plan_stage_request.py
huaweicloudsdkdws/v2/model/add_workload_plan_stage_response.py
huaweicloudsdkdws/v2/model/add_workload_queue_request.py
huaweicloudsdkdws/v2/model/add_workload_queue_response.py
huaweicloudsdkdws/v2/model/add_workload_rule_request.py
huaweicloudsdkdws/v2/model/add_workload_rule_response.py
huaweicloudsdkdws/v2/model/alarm_config_response.py
huaweicloudsdkdws/v2/model/alarm_detail_response.py
huaweicloudsdkdws/v2/model/alarm_statistic_response.py
huaweicloudsdkdws/v2/model/alarm_sub_request.py
huaweicloudsdkdws/v2/model/alarm_sub_update_request.py
huaweicloudsdkdws/v2/model/alarm_subscription_response.py
huaweicloudsdkdws/v2/model/associate_eip_request.py
huaweicloudsdkdws/v2/model/associate_eip_response.py
huaweicloudsdkdws/v2/model/associate_elb_request.py
huaweicloudsdkdws/v2/model/associate_elb_response.py
huaweicloudsdkdws/v2/model/audit_dump_record.py
huaweicloudsdkdws/v2/model/availability_zone.py
huaweicloudsdkdws/v2/model/backup_strategy_detail.py
huaweicloudsdkdws/v2/model/backup_strategy_request.py
huaweicloudsdkdws/v2/model/batch_create_cluster_cn_request.py
huaweicloudsdkdws/v2/model/batch_create_cluster_cn_response.py
huaweicloudsdkdws/v2/model/batch_create_cn.py
huaweicloudsdkdws/v2/model/batch_create_resource_tag.py
huaweicloudsdkdws/v2/model/batch_create_resource_tag_request.py
huaweicloudsdkdws/v2/model/batch_create_resource_tag_response.py
huaweicloudsdkdws/v2/model/batch_create_resource_tags.py
huaweicloudsdkdws-3.1.184.dist-info/METADATA
huaweicloudsdkdws-3.1.184.dist-info/WHEEL
huaweicloudsdkdws-3.1.184.dist-info/licenses/LICENSE
huaweicloudsdkdws-3.1.184.dist-info/RECORD
